alexander_shlyaev_package/__init__.py
alexander_shlyaev_package/common_functions.py
alexander_shlyaev_package/db_functions.py
alexander_shlyaev_package-0.1.dist-info/METADATA
alexander_shlyaev_package-0.1.dist-info/WHEEL
alexander_shlyaev_package-0.1.dist-info/top_level.txt
alexander_shlyaev_package-0.1.dist-info/RECORD
