Metadata-Version: 2.1
Name: alexander-shlyaev-package
Version: 0.1
Summary: This  is very useful package
Home-page: UNKNOWN
Author: me
Author-email: some@email.com
License: UNKNOWN
Platform: UNKNOWN
